dj_database_url.py
django_database_url-1.0.3.dist-info/LICENSE
django_database_url-1.0.3.dist-info/METADATA
django_database_url-1.0.3.dist-info/WHEEL
django_database_url-1.0.3.dist-info/top_level.txt
django_database_url-1.0.3.dist-info/RECORD
