Metadata-Version: 2.1
Name: django-database-url
Version: 1.0.3
Summary: Use Database URLs in your Django Application.
Home-page: https://github.com/tend/dj-database-url
Author: Rati Matchavariani
Author-email: rati.matchavariani@hellotend.com
License: BSD
Platform: any
Classifier: Environment :: Web Environment
Classifier: Framework :: Django
Classifier: Framework :: Django :: 3.0
Classifier: Intended Audience :: Developers
Classifier: License :: OSI Approved :: BSD License
Classifier: Operating System :: OS Independent
Classifier: Programming Language :: Python
Classifier: Topic :: Internet :: WWW/HTTP :: Dynamic Content
Classifier: Topic :: Software Development :: Libraries :: Python Modules
Classifier: Programming Language :: Python
Classifier: Programming Language :: Python :: 3.8
License-File: LICENSE
